qiskit_quantier/__init__.py
qiskit_quantier/api.py
qiskit_quantier/quantier.py
qiskit_quantier-0.9.5.dist-info/METADATA
qiskit_quantier-0.9.5.dist-info/WHEEL
qiskit_quantier-0.9.5.dist-info/top_level.txt
qiskit_quantier-0.9.5.dist-info/RECORD
