Metadata-Version: 2.1
Name: qiskit-quantier
Version: 0.9.5
Summary: QUANTier version of provider for Qiskit
Classifier: Programming Language :: Python :: 3
Classifier: License :: OSI Approved :: MIT License
Classifier: Operating System :: OS Independent
Requires-Python: >=3.8
Requires-Dist: qiskit
Requires-Dist: qiskit-aer
Requires-Dist: python-dotenv
Requires-Dist: mysql-connector-python
Requires-Dist: httpx
